objective_lol-0.0.2.dist-info/WHEEL
objective_lol-0.0.2.dist-info/METADATA
objective_lol-0.0.2.dist-info/top_level.txt
objective_lol-0.0.2.dist-info/RECORD
objective_lol/api.c
objective_lol/build.py
objective_lol/_api.cpython-310-aarch64-linux-gnu.h
objective_lol/api.py
objective_lol/olol.py
objective_lol/__init__.py
objective_lol/_api.cpython-310-aarch64-linux-gnu.so
objective_lol/api.go
objective_lol/api_go.h
objective_lol/go.py
