Metadata-Version: 2.4
Name: objective_lol
Version: 0.0.2
Summary: Python bindings for Objective-LOL
Home-page: https://github.com/bjia56/objective-lol
Author: Brett Jia
Author-email: dev.bjia56@gmail.com
Classifier: Programming Language :: Python :: 3
Classifier: License :: OSI Approved :: MIT License
Dynamic: author
Dynamic: author-email
Dynamic: classifier
Dynamic: description
Dynamic: description-content-type
Dynamic: home-page
Dynamic: summary
